aioswitchbotmeter/__init__.py
aioswitchbotmeter-0.1.1.dist-info/WHEEL
aioswitchbotmeter-0.1.1.dist-info/METADATA
aioswitchbotmeter-0.1.1.dist-info/RECORD
