Metadata-Version: 2.1
Name: aioswitchbotmeter
Version: 0.1.1
Summary: AsyncIO-compatible SwitchBot Meter library
Author: David Francos
Author-email: opensource@davidfrancos.net
Requires-Python: >=3.8,<4.0
Classifier: Programming Language :: Python :: 3
Classifier: Programming Language :: Python :: 3.8
Requires-Dist: bluepy (>=1.3.0,<2.0.0)
